{
  "id": "6bbb88ea-57b9-41a7-abc2-2d3e4e0c7ddc",
  "name": "The Czech Benoni",
  "shortName": "The Czech Benoni",
  "description": "The Czech Benoni is an easy-to-learn defense that can become your main weapon with Black against 1.d4. You simply lock up the position and launch a huge attack.",
  "color": "B",
  "imageUrl": "https://res.cloudinary.com/chessly/image/upload/v1734715262/mcchkshweytzaurc47sd.png",
  "tags": [
    "Black Openings"
  ],
  "createdAt": 1734100022,
  "_kind": "openings",
  "_idx": 14,
  "_name": "The Czech Benoni"
}