{
  "id": "10bae42b-1b55-46a1-b719-4ca05215d1ce",
  "name": "Quiz 2",
  "type": "VANILLA_QUIZ",
  "videoVimeoId": null,
  "videoDurationSec": null,
  "study": null,
  "quiz": {
    "question": "Black is down material and you should simplify and win. \n\nNe4 is a way to try and do that. Is this a good move, or is there something wrong with it?",
    "answers": [
      {
        "text": "It's a bad move.",
        "feedback": {
          "text": "Ne4 and Black plays Nf3+. After gxf3, Black gets an easy draw with Bxh2+. White could even lose if they don't go for the draw!",
          "arrows": {
            "threats": [],
            "opportunities": [
              "d6-h2",
              "e5-f3"
            ]
          },
          "highlights": {
            "threats": [
              "h2"
            ],
            "opportunities": []
          }
        },
        "comment": null,
        "afterMoveFen": null
      }
    ],
    "distractors": [
      {
        "text": "It's a great move to trade pieces!",
        "feedback": {
          "text": "Are you sure? Can you consider some sacrifices Black may have?",
          "arrows": null,
          "highlights": null
        },
        "comment": null,
        "afterMoveFen": null
      },
      {
        "text": "It's ok, but Bf4 is better.",
        "feedback": {
          "text": "Bf4 is better, but the move Ne4 is not ok. Therefore this statement is false.",
          "arrows": null,
          "highlights": null
        },
        "comment": null,
        "afterMoveFen": null
      }
    ],
    "positionFen": "2kr1bnr/pppb2p1/5pp1/4n3/8/2N5/PPP1QPPP/R1B2RK1 b - - 1 1",
    "arrows": {
      "threats": [],
      "opportunities": [
        "c3-e4"
      ]
    },
    "highlights": null,
    "contextMove": {
      "san": "Bd6",
      "afterMoveFen": "2kr2nr/pppb2p1/3b1pp1/4n3/8/2N5/PPP1QPPP/R1B2RK1 w - - 2 2"
    }
  },
  "drill": null
}